{
	"file_path": "C:\\Users\\Lance\\AppData\\Local\\Packages\\Microsoft.MinecraftUWP_8wekyb3d8bbwe\\LocalState\\games\\com.mojang\\development_behavior_packs\\terraria BP\\recipes\\load_ironbow_recipe.json",
	"file_type": "recipe",
	"format_version": 1,
	"file_uuid": "0325626e_0843_4992_be22_37cdfe3ea720",
	"file_version": 5,
	"cache_content": {
		"children": [
			{
				"data": "1.16.100",
				"key": "format_version"
			},
			{
				"open": {
					"format_version": "1.16.100",
					"minecraft:recipe_shapeless": {
						"description": {
							"identifier": "terrariamod:load_ironbow_recipe"
						},
						"tags": [
							"crafting_table"
						],
						"ingredients": [
							{
								"item": "terrariamod:ironbow_unloaded"
							},
							{
								"item": "terrariamod:woodenarrow",
								"count": 8
							}
						],
						"result": [
							{
								"item": "terrariamod:ironbow_loaded"
							}
						]
					}
				},
				"key": "minecraft:recipe_shapeless",
				"children": [
					{
						"open": {
							"description": {
								"identifier": "terrariamod:load_ironbow_recipe"
							},
							"tags": [
								"crafting_table"
							],
							"ingredients": [
								{
									"item": "terrariamod:ironbow_unloaded"
								},
								{
									"item": "terrariamod:woodenarrow",
									"count": 8
								}
							],
							"result": [
								{
									"item": "terrariamod:ironbow_loaded"
								}
							]
						},
						"key": "description",
						"is_minified": true,
						"children": {
							"identifier": "terrariamod:load_ironbow_recipe"
						}
					},
					{
						"open": {
							"description": {
								"identifier": "terrariamod:load_ironbow_recipe"
							},
							"tags": [
								"crafting_table"
							],
							"ingredients": [
								{
									"item": "terrariamod:ironbow_unloaded"
								},
								{
									"item": "terrariamod:woodenarrow",
									"count": 8
								}
							],
							"result": [
								{
									"item": "terrariamod:ironbow_loaded"
								}
							]
						},
						"key": "tags",
						"is_minified": true,
						"children": [
							"crafting_table"
						]
					},
					{
						"open": {
							"description": {
								"identifier": "terrariamod:load_ironbow_recipe"
							},
							"tags": [
								"crafting_table"
							],
							"ingredients": [
								{
									"item": "terrariamod:ironbow_unloaded"
								},
								{
									"item": "terrariamod:woodenarrow",
									"count": 8
								}
							],
							"result": [
								{
									"item": "terrariamod:ironbow_loaded"
								}
							]
						},
						"key": "ingredients",
						"children": [
							{
								"open": [
									{
										"item": "terrariamod:ironbow_unloaded"
									},
									{
										"item": "terrariamod:woodenarrow",
										"count": 8
									}
								],
								"is_minified": true,
								"children": {
									"item": "terrariamod:ironbow_unloaded"
								}
							},
							{
								"open": [
									{
										"item": "terrariamod:ironbow_unloaded"
									},
									{
										"item": "terrariamod:woodenarrow",
										"count": 8
									}
								],
								"is_minified": true,
								"children": {
									"item": "terrariamod:woodenarrow",
									"count": 8
								}
							}
						]
					},
					{
						"open": {
							"description": {
								"identifier": "terrariamod:load_ironbow_recipe"
							},
							"tags": [
								"crafting_table"
							],
							"ingredients": [
								{
									"item": "terrariamod:ironbow_unloaded"
								},
								{
									"item": "terrariamod:woodenarrow",
									"count": 8
								}
							],
							"result": [
								{
									"item": "terrariamod:ironbow_loaded"
								}
							]
						},
						"key": "result",
						"children": [
							{
								"open": [
									{
										"item": "terrariamod:ironbow_loaded"
									}
								],
								"is_minified": true,
								"children": {
									"item": "terrariamod:ironbow_loaded"
								}
							}
						]
					}
				]
			}
		]
	}
}