{
	"file_path": "C:\\Users\\Lance\\AppData\\Local\\Packages\\Microsoft.MinecraftUWP_8wekyb3d8bbwe\\LocalState\\games\\com.mojang\\development_behavior_packs\\terraria BP\\recipes\\poisonedknife_recipe.json",
	"file_type": "recipe",
	"format_version": 1,
	"file_uuid": "fa398e81_64d5_430c_9a00_4aa59856d018",
	"file_version": 3,
	"cache_content": {
		"children": [
			{
				"data": "1.16.100",
				"key": "format_version"
			},
			{
				"open": {
					"format_version": "1.16.100",
					"minecraft:recipe_shapeless": {
						"description": {
							"identifier": "terrariamod:poisonedknife_recipe"
						},
						"tags": [
							"crafting_table"
						],
						"ingredients": [
							{
								"item": "terrariamod:throwingknife",
								"count": 5
							},
							{
								"item": "terrariamod:viciousmushroom",
								"count": 1
							}
						],
						"result": [
							{
								"item": "terrariamod:poisonedknife",
								"count": 5
							}
						]
					}
				},
				"key": "minecraft:recipe_shapeless",
				"children": [
					{
						"open": {
							"description": {
								"identifier": "terrariamod:poisonedknife_recipe"
							},
							"tags": [
								"crafting_table"
							],
							"ingredients": [
								{
									"item": "terrariamod:throwingknife",
									"count": 5
								},
								{
									"item": "terrariamod:viciousmushroom",
									"count": 1
								}
							],
							"result": [
								{
									"item": "terrariamod:poisonedknife",
									"count": 5
								}
							]
						},
						"key": "description",
						"is_minified": true,
						"children": {
							"identifier": "terrariamod:poisonedknife_recipe"
						}
					},
					{
						"open": {
							"description": {
								"identifier": "terrariamod:poisonedknife_recipe"
							},
							"tags": [
								"crafting_table"
							],
							"ingredients": [
								{
									"item": "terrariamod:throwingknife",
									"count": 5
								},
								{
									"item": "terrariamod:viciousmushroom",
									"count": 1
								}
							],
							"result": [
								{
									"item": "terrariamod:poisonedknife",
									"count": 5
								}
							]
						},
						"key": "tags",
						"is_minified": true,
						"children": [
							"crafting_table"
						]
					},
					{
						"open": {
							"description": {
								"identifier": "terrariamod:poisonedknife_recipe"
							},
							"tags": [
								"crafting_table"
							],
							"ingredients": [
								{
									"item": "terrariamod:throwingknife",
									"count": 5
								},
								{
									"item": "terrariamod:viciousmushroom",
									"count": 1
								}
							],
							"result": [
								{
									"item": "terrariamod:poisonedknife",
									"count": 5
								}
							]
						},
						"key": "ingredients",
						"children": [
							{
								"open": [
									{
										"item": "terrariamod:throwingknife",
										"count": 5
									},
									{
										"item": "terrariamod:viciousmushroom",
										"count": 1
									}
								],
								"is_minified": true,
								"children": {
									"item": "terrariamod:throwingknife",
									"count": 5
								}
							},
							{
								"open": [
									{
										"item": "terrariamod:throwingknife",
										"count": 5
									},
									{
										"item": "terrariamod:viciousmushroom",
										"count": 1
									}
								],
								"is_minified": true,
								"children": {
									"item": "terrariamod:viciousmushroom",
									"count": 1
								}
							}
						]
					},
					{
						"open": {
							"description": {
								"identifier": "terrariamod:poisonedknife_recipe"
							},
							"tags": [
								"crafting_table"
							],
							"ingredients": [
								{
									"item": "terrariamod:throwingknife",
									"count": 5
								},
								{
									"item": "terrariamod:viciousmushroom",
									"count": 1
								}
							],
							"result": [
								{
									"item": "terrariamod:poisonedknife",
									"count": 5
								}
							]
						},
						"key": "result",
						"children": [
							{
								"open": [
									{
										"item": "terrariamod:poisonedknife",
										"count": 5
									}
								],
								"is_minified": true,
								"children": {
									"item": "terrariamod:poisonedknife",
									"count": 5
								}
							}
						]
					}
				]
			}
		]
	}
}