{
	"file_path": "C:\\Users\\LANCE.LEGAUX\\AppData\\Local\\Packages\\Microsoft.MinecraftUWP_8wekyb3d8bbwe\\LocalState\\games\\com.mojang\\development_behavior_packs\\terraria BP\\biomes\\warped_forest.biome.json",
	"file_type": "biome",
	"format_version": 1,
	"file_uuid": "14fdd5b0_95fb_42b3_8365_fc1372e30620",
	"file_version": 5,
	"cache_content": {
		"children": [
			{
				"data": "1.13.0",
				"key": "format_version"
			},
			{
				"open": {
					"format_version": "1.13.0",
					"minecraft:biome": {
						"description": {
							"identifier": "warped_forest"
						},
						"components": {
							"minecraft:climate": {
								"downfall": 0,
								"snow_accumulation": [
									0,
									0.125
								],
								"temperature": 2
							},
							"minecraft:overworld_height": {
								"noise_type": "extreme"
							},
							"minecraft:surface_parameters": {
								"sea_floor_depth": 7,
								"sea_floor_material": "terrariamod:ash",
								"foundation_material": "terrariamod:ash",
								"mid_material": "terrariamod:ash",
								"top_material": "terrariamod:ash",
								"sea_material": "minecraft:lava"
							},
							"minecraft:nether_generation_rules": {
								"target_temperature": -0.5,
								"target_humidity": 0,
								"target_altitude": 0,
								"target_weirdness": 0,
								"weight": 0.175
							},
							"underworld": {},
							"nether": {}
						}
					}
				},
				"key": "minecraft:biome",
				"children": [
					{
						"open": {
							"description": {
								"identifier": "warped_forest"
							},
							"components": {
								"minecraft:climate": {
									"downfall": 0,
									"snow_accumulation": [
										0,
										0.125
									],
									"temperature": 2
								},
								"minecraft:overworld_height": {
									"noise_type": "extreme"
								},
								"minecraft:surface_parameters": {
									"sea_floor_depth": 7,
									"sea_floor_material": "terrariamod:ash",
									"foundation_material": "terrariamod:ash",
									"mid_material": "terrariamod:ash",
									"top_material": "terrariamod:ash",
									"sea_material": "minecraft:lava"
								},
								"minecraft:nether_generation_rules": {
									"target_temperature": -0.5,
									"target_humidity": 0,
									"target_altitude": 0,
									"target_weirdness": 0,
									"weight": 0.175
								},
								"underworld": {},
								"nether": {}
							}
						},
						"key": "description",
						"is_minified": true,
						"children": {
							"identifier": "warped_forest"
						}
					},
					{
						"key": "components",
						"is_minified": true,
						"children": {
							"minecraft:climate": {
								"downfall": 0,
								"snow_accumulation": [
									0,
									0.125
								],
								"temperature": 2
							},
							"minecraft:overworld_height": {
								"noise_type": "extreme"
							},
							"minecraft:surface_parameters": {
								"sea_floor_depth": 7,
								"sea_floor_material": "terrariamod:ash",
								"foundation_material": "terrariamod:ash",
								"mid_material": "terrariamod:ash",
								"top_material": "terrariamod:ash",
								"sea_material": "minecraft:lava"
							},
							"minecraft:nether_generation_rules": {
								"target_temperature": -0.5,
								"target_humidity": 0,
								"target_altitude": 0,
								"target_weirdness": 0,
								"weight": 0.175
							},
							"underworld": {},
							"nether": {}
						}
					}
				]
			}
		]
	}
}