{
	"format_version": "1.16.100",
	"minecraft:block": {
		"description": {
			"identifier": "terrariamod:purity_chest",
			"register_to_creative_menu": true
		},
		"components": {
			"minecraft:geometry": "geometry.chest",
			"minecraft:material_instances": {
				"*": {
					"texture": "chest",
					"render_method": "alpha_test"
				}
			},
			"minecraft:destroy_time": 999,
			"tag:terrariamod:wood": {},
			"minecraft:loot": "loot_tables/blocks/purity_chest_item.json",
			"minecraft:ticking": {
				"looping": false,
				"range": [
					0.1,
					0.1
				],
				"on_tick": {
					"event": "terrariamod:create_dummy"
				}
			},
			"minecraft:on_player_destroyed": {
				"event": "terrariamod:destroy_dummy",
				"target": "self"
			}
		},
		"events": {
			"terrariamod:create_dummy": {
				"run_command": {
					"command": [
						"summon terrariamod:chest_dummy ~~~"
					]
				}
			},
			"terrariamod:destroy_dummy": {
				"run_command": {
					"command": [
						"kill @e[type=terrariamod:chest_dummy,r=2]"
					]
				}
			}
		}
	}
}